bcf_api_xml/Schemas/bcf.version
bcf_api_xml/Schemas/markup.xsd
bcf_api_xml/Schemas/project.xsd
bcf_api_xml/Schemas/version.xsd
bcf_api_xml/Schemas/visinfo.xsd
bcf_api_xml/__init__.py
bcf_api_xml/errors.py
bcf_api_xml/export/__init__.py
bcf_api_xml/export/excel.py
bcf_api_xml/export/zip.py
bcf_api_xml/import_zip.py
bcf_api_xml/models/ClippingPlane.py
bcf_api_xml/models/Color.py
bcf_api_xml/models/Comment.py
bcf_api_xml/models/Component.py
bcf_api_xml/models/Line.py
bcf_api_xml/models/OrthogonalCamera.py
bcf_api_xml/models/PerspectiveCamera.py
bcf_api_xml/models/Topic.py
bcf_api_xml/models/ViewSetupHints.py
bcf_api_xml/models/Viewpoint.py
bcf_api_xml/models/Visibility.py
bcf_api_xml/models/VisualizationInfo.py
bcf_api_xml/models/XYZ.py
bcf_api_xml/models/__init__.py
bcf_api_xml-0.4.19.dist-info/METADATA
bcf_api_xml-0.4.19.dist-info/WHEEL
bcf_api_xml-0.4.19.dist-info/RECORD
