Metadata-Version: 2.1
Name: bcf-api-xml
Version: 0.4.19
Summary: Convert BCF-API to BCF-XML
Home-page: https://github.com/bimdata/BCF-API-XML-translator
License: MIT
Author: Hugo Duroux
Author-email: hugo@bimdata.io
Requires-Python: >=3.10,<4.0
Classifier: License :: OSI Approved :: MIT License
Classifier: Programming Language :: Python :: 3
Classifier: Programming Language :: Python :: 3.10
Classifier: Programming Language :: Python :: 3.11
Classifier: Programming Language :: Python :: 3.12
Classifier: Programming Language :: Python :: 3.13
Requires-Dist: generateDS (>=2.35.13,<3.0.0)
Requires-Dist: lxml (>=5.3.1,<6.0.0)
Requires-Dist: pillow (>=11.1.0,<12.0.0)
Requires-Dist: python-dateutil (>=2.8.0,<3.0.0)
Requires-Dist: xlsxwriter (>=3.2.2,<4.0.0)
Project-URL: Repository, https://github.com/bimdata/BCF-API-XML-translator
